git_peek/__init__.py
git_peek/__main__.py
git_peek/parse_arguments.py
git_peek-1.3.dist-info/AUTHORS.rst
git_peek-1.3.dist-info/LICENSE.txt
git_peek-1.3.dist-info/METADATA
git_peek-1.3.dist-info/WHEEL
git_peek-1.3.dist-info/entry_points.txt
git_peek-1.3.dist-info/top_level.txt
git_peek-1.3.dist-info/RECORD
