Metadata-Version: 2.1
Name: git-peek
Version: 1.3
Summary: Python script to peek what various commits someone did
Home-page: UNKNOWN
Author: Sherry Ummen
Author-email: sherry.ummen@gmail.com
License: mit
Platform: any
Classifier: Development Status :: 4 - Beta
Classifier: Programming Language :: Python
